CHANGELOG.rst
LICENSE
MANIFEST.in
README.rst
setup.py
bin/git-bigfile
git_bigfile.egg-info/PKG-INFO
git_bigfile.egg-info/SOURCES.txt
git_bigfile.egg-info/dependency_links.txt
git_bigfile.egg-info/requires.txt
git_bigfile.egg-info/top_level.txt
gitbigfile/__init__.py
gitbigfile/command.py
gitbigfile/transport.py
gitbigfile/util.py