Metadata-Version: 1.0
Name: git-bigfile
Version: 0.1.2
Summary: git-bigfile allows you to use Git with large files without storing the file in Git itself
Home-page: https://github.com/beenje/git-bigfile
Author: Benjamin Bertrand
Author-email: beenje@gmail.com
License: MIT
Platform: UNKNOWN
Classifier: Development Status :: 4 - Beta
Classifier: Topic :: Software Development
Classifier: License :: OSI Approved :: MIT License
Classifier: Intended Audience :: Developers
Classifier: Programming Language :: Python
